{
  "notices": [
    {
      "author": "PaperStream Admin",
      "category": "General",
      "date": "Apr 23, 2026",
      "id": "B1B1B050",
      "isActive": false,
      "message": "Thank you to all of you friends... Today you seriously followed the instructions of the Honorable Principal... Please maintain the same spirit in the next two days also... so that the prestige of the institution is maintained in front of the presenters coming from outside.\n\nBoth the boys and girls are requested to be present tomorrow at 2 pm and sit with them in the program so that they can enjoy the program while remaining disciplined.\n\nArrangements for refreshments have also been made for the students tomorrow.\n\nAffectionately",
      "priority": "normal",
      "time": "09:28 PM",
      "title": "Notice By Yogi Sir"
    },
    {
      "author": "PaperStream Admin",
      "category": "Urgent",
      "date": "Apr 23, 2026",
      "id": "2108FCCD",
      "isActive": true,
      "message": "Tomorrow there will be a test on these questions uploaded on group and the assignment will be checked. assiment was also uploaded on group ",
      "priority": "normal",
      "time": "07:22 PM",
      "title": "Em Test As Assistant "
    },
    {
      "author": "PaperStream Admin",
      "category": "General",
      "date": "Apr 21, 2026",
      "id": "7A92A631",
      "isActive": true,
      "message": "it 2 test will conduct on May 1 Week",
      "priority": "normal",
      "time": "11:50 AM",
      "title": "IT Test "
    },
    {
      "author": "PaperStream Admin",
      "category": "General",
      "date": "Apr 21, 2026",
      "id": "15274BDF",
      "isActive": true,
      "message": "It assiment as practically was summited on Friday mack sure you will complete it",
      "priority": "normal",
      "time": "11:45 AM",
      "title": "It Notice "
    }
  ]
}